peacedeath/__init__.py
peacedeath/calibration.py
peacedeath/experiment.py
peacedeath/od_measurement.py
peacedeath/photodiodes.py
peacedeath/pumps.py
peacedeath/telegram.py
peacedeath/valves.py
peacedeath/pm/__init__.py
peacedeath/pm/device_messages_pb2.py
peacedeath/pm/network_messages_pb2.py
peacedeath/pm/protobuf_to_dict.py
peacedeath-0.46.dist-info/METADATA
peacedeath-0.46.dist-info/WHEEL
peacedeath-0.46.dist-info/top_level.txt
peacedeath-0.46.dist-info/zip-safe
peacedeath-0.46.dist-info/RECORD
